django_fernet_fields_py_311-0.6.1.dist-info/licenses/AUTHORS.rst
django_fernet_fields_py_311-0.6.1.dist-info/licenses/LICENSE.txt
fernet_fields/__init__.py
fernet_fields/fields.py
fernet_fields/hkdf.py
fernet_fields/test/__init__.py
fernet_fields/test/models.py
fernet_fields/test/test_fields.py
fernet_fields/test/settings/__init__.py
fernet_fields/test/settings/base.py
fernet_fields/test/settings/pg.py
fernet_fields/test/settings/sqlite.py
django_fernet_fields_py_311-0.6.1.dist-info/METADATA
django_fernet_fields_py_311-0.6.1.dist-info/WHEEL
django_fernet_fields_py_311-0.6.1.dist-info/top_level.txt
django_fernet_fields_py_311-0.6.1.dist-info/RECORD
